[
  {
    "name": "Apple",
    "image": "https://upload.wikimedia.org/wikipedia/commons/thumb/1/15/Red_Apple.jpg/265px-Red_Apple.jpg",
    "price": 35,
    "sugar": [
      {
        "uom": "gram",
        "amount": "0.1"
      }
    ],
    "type": "fruit"
  },
  {
    "name": "Banana",
    "image": "https://upload.wikimedia.org/wikipedia/commons/thumb/4/44/Bananas_white_background_DS.jpg/320px-Bananas_white_background_DS.jpg",
    "price": 12,
    "sugar": [
      {
        "uom": "gram",
        "amount": "0.12"
      }
    ],
    "type": "fruit",
    "colour": [
      "yellow"
    ]
  },
  {
    "name": "Grapes",
    "image": "https://upload.wikimedia.org/wikipedia/commons/thumb/b/bb/Table_grapes_on_white.jpg/320px-Table_grapes_on_white.jpg",
    "weight": 0.1,
    "price": 45,
    "sugar": [
      {
        "uom": "gram",
        "amount": "0.16"
      }
    ],
    "type": "fruit",
    "colour": [
      "red",
      "green"
    ]
  },
  {
    "name": "Pineapple",
    "image": "https://upload.wikimedia.org/wikipedia/commons/thumb/c/cb/Pineapple_and_cross_section.jpg/286px-Pineapple_and_cross_section.jpg",
    "price": 200,
    "sugar": [
      {
        "uom": "gram",
        "amount": "0.1"
      }
    ],
    "type": "fruit",
    "colour": [
      "yellow"
    ]
  },
  {
    "name": "Carrot",
    "image": "https://upload.wikimedia.org/wikipedia/commons/thumb/f/fc/Carrot_bunches.jpg/250px-Carrot_bunches.jpg",
    "price": 20,
    "sugar": [
      {
        "uom": "gram",
        "amount": "0.047"
      }
    ],
    "type": "vegetable",
    "colour": [
      "orange",
      "purple"
    ]
  },
  {
    "name": "Potato",
    "image": "https://upload.wikimedia.org/wikipedia/commons/thumb/1/14/2010-06-19-supermarkt-by-RalfR-29.jpg/120px-2010-06-19-supermarkt-by-RalfR-29.jpg",
    "price": 23,
    "sugar": [
      {
        "uom": "gram",
        "amount": "0.47"
      }
    ],
    "type": "vegetable",
    "colour": [
      "red",
      "brown"
    ]
  },
  {
    "name": "Green Beans",
    "image": "https://upload.wikimedia.org/wikipedia/commons/thumb/f/fc/Carrot_bunches.jpg/250px-Carrot_bunches.jpg",
    "price": 20,
    "sugar": [
      {
        "uom": "gram",
        "amount": "0.047"
      }
    ],
    "type": "vegetable",
    "colour": [
      "red"
    ]
  }
]